odoo10_addon_product_variant_supplierinfo-10.0.1.0.0-py2.7-nspkg.pth
odoo10_addon_product_variant_supplierinfo-10.0.1.0.0.dist-info/top_level.txt
odoo10_addon_product_variant_supplierinfo-10.0.1.0.0.dist-info/WHEEL
odoo10_addon_product_variant_supplierinfo-10.0.1.0.0.dist-info/RECORD
odoo10_addon_product_variant_supplierinfo-10.0.1.0.0.dist-info/metadata.json
odoo10_addon_product_variant_supplierinfo-10.0.1.0.0.dist-info/DESCRIPTION.rst
odoo10_addon_product_variant_supplierinfo-10.0.1.0.0.dist-info/METADATA
odoo10_addon_product_variant_supplierinfo-10.0.1.0.0.dist-info/namespace_packages.txt
odoo/addons/product_variant_supplierinfo/__manifest__.py
odoo/addons/product_variant_supplierinfo/__init__.py
odoo/addons/product_variant_supplierinfo/README.rst
odoo/addons/product_variant_supplierinfo/models/product_product.py
odoo/addons/product_variant_supplierinfo/models/__init__.py
odoo/addons/product_variant_supplierinfo/models/procurement.py
odoo/addons/product_variant_supplierinfo/models/product_supplierinfo.py
odoo/addons/product_variant_supplierinfo/i18n/it.po
odoo/addons/product_variant_supplierinfo/i18n/es.po
odoo/addons/product_variant_supplierinfo/i18n/ro.po
odoo/addons/product_variant_supplierinfo/i18n/sl.po
odoo/addons/product_variant_supplierinfo/i18n/fr.po
odoo/addons/product_variant_supplierinfo/i18n/pt_BR.po
odoo/addons/product_variant_supplierinfo/views/product_product_view.xml
odoo/addons/product_variant_supplierinfo/views/product_supplierinfo_view.xml
odoo/addons/product_variant_supplierinfo/tests/test_procurement.py
odoo/addons/product_variant_supplierinfo/tests/test_product_supplierinfo.py
odoo/addons/product_variant_supplierinfo/tests/__init__.py
odoo/addons/product_variant_supplierinfo/demo/procurement_demo.xml
odoo/addons/product_variant_supplierinfo/demo/product_demo.xml
odoo/addons/product_variant_supplierinfo/static/description/icon.png
