Metadata-Version: 2.0
Name: odoo10-addon-product-variant-supplierinfo
Version: 10.0.1.0.0
Summary: Supplier info to product variant scope
Home-page: UNKNOWN
Author: Tecnativa, Akretion,Odoo Community Association (OCA)
Author-email: support@odoo-community.org
License: UNKNOWN
Platform: UNKNOWN
Requires-Dist: odoo (<10.1dev,>=10.0)
Classifier: Programming Language :: Python :: 2.7
Classifier: Framework :: Odoo
